Workbook

Sheet PriceList
A1: Category | B1: Service | C1: Price
A2: Hair | B2: Blowdry | C2: 99
A3: Hair | B3: Haircut | C3: 149
A4: Hair | B4: Iron | C4: 199
A5: Hair | B5: Hair Spa | C5: 349
A6: Hair | B6: Hair Botox Treatment | C6: 499
A7: Hair | B7: Keratin Mask | C7: 499
A8: Hair | B8: Color | C8: 699
A9: Hair | B9: Rebond | C9: 1499
A10: Hair | B10: Rebond Hair Botox | C10: 1999
A11: Hair | B11: Rebond / Color | C11: 2199
A12: Hair | B12: Rebond / Color / Brazilian | C12: 3199
A13: Hair | B13: Kerabond | C13: 1999
... A32: Other | B32: Hair & Make up (Wedding/Debut) | C32: 1499

Sheet Settings
A1: Product Cost % of Sales | B1: 0.2
A2: Fixed Rent | B2: 15000
A3: Electricity | B3: 5000
A4: Water | B4: 500
A6: Senior Base Salary | B6: 12000
A7: Junior Base Salary | B7: 9000
A8: Nail Tech Base Salary | B8: 8000

Sheet Transactions
A1: Date | B1: Day | C1: Service | D1: Category | E1: Staff | F1: Price | G1: Commission (10%)
A2: 45658 | B2: Wed | C2: Manicure | D2: Nail | E2: Nail Tech | F2: 119 | G2: =F2*0.10 -> 0
A3: 45658 | B3: Wed | C3: Foot Spa | D3: Nail | E3: Nail Tech | F3: 299 | G3: =F3*0.10 -> 0
A4: 45658 | B4: Wed | C4: Blowdry | D4: Hair | E4: Senior Stylist | F4: 99 | G4: =F4*0.10 -> 0
A5: 45658 | B5: Wed | C5: Blowdry | D5: Hair | E5: Junior Stylist | F5: 99 | G5: =F5*0.10 -> 0
A6: 45658 | B6: Wed | C6: Brazilian | D6: Hair | E6: Junior Stylist | F6: 1499 | G6: =F6*0.10 -> 0
A7: 45658 | B7: Wed | C7: Balayage / Color | D7: Hair | E7: Junior Stylist | F7: 2499 | G7: =F7*0.10 -> 0
A8: 45658 | B8: Wed | C8: Blowdry | D8: Hair | E8: Senior Stylist | F8: 99 | G8: =F8*0.10 -> 0
A9: 45658 | B9: Wed | C9: Iron | D9: Hair | E9: Senior Stylist | F9: 199 | G9: =F9*0.10 -> 0
A10: 45658 | B10: Wed | C10: Pedicure | D10: Nail | E10: Nail Tech | F10: 149 | G10: =F10*0.10 -> 0
A11: 45658 | B11: Wed | C11: Keratin Mask | D11: Hair | E11: Senior Stylist | F11: 499 | G11: =F11*0.10 -> 0
A12: 45658 | B12: Wed | C12: Manicure / Pedicure | D12: Nail | E12: Nail Tech | F12: 269 | G12: =F12*0.10 -> 0
A13: 45658 | B13: Wed | C13: Foot Spa / Pedicure | D13: Nail | E13: Nail Tech | F13: 399 | G13: =F13*0.10 -> 0
... A333: 45687 | B333: Thu | C333: Haircut | D333: Hair | E333: Senior Stylist | F333: 149 | G333: =F333*0.10 -> 0

Sheet Summary
A1: Metric | B1: Amount (PHP)
A2: Total Sales | B2: =SUM(Transactions!F:F) -> 0
A3: Product Cost | B3: =B2*Settings!$B$1 -> 0
A4: Fixed Salon Expenses (Rent+Utilities) | B4: =Settings!$B$2+Settings!$B$3+Settings!$B$4 -> 0
A5: Senior Sales | B5: =SUMIF(Transactions!E:E,"Senior Stylist",Transactions!F:F) -> 0
A6: Junior Sales | B6: =SUMIF(Transactions!E:E,"Junior Stylist",Transactions!F:F) -> 0
A7: Nail Tech Sales | B7: =SUMIF(Transactions!E:E,"Nail Tech",Transactions!F:F) -> 0
A8: Senior Base Salary | B8: =Settings!$B$6 -> 0
A9: Junior Base Salary | B9: =Settings!$B$7 -> 0
A10: Nail Tech Base Salary | B10: =Settings!$B$8 -> 0
A11: Senior Incentive | B11: =IF(B5<100000,0,2000+500*INT((B5-100000)/5000)) -> 0
A12: Junior Incentive | B12: =IF(B6<100000,0,2000+500*INT((B6-100000)/5000)) -> 0
A13: Nail Tech Incentive | B13: =IF(B7<45000,0,1500+500*(1+INT((B7-45000)/5000))) -> 0
A14: Senior Commission (10%) | B14: =SUMIF(Transactions!E:E,"Senior Stylist",Transactions!G:G) -> 0
A15: Junior Commission (10%) | B15: =SUMIF(Transactions!E:E,"Junior Stylist",Transactions!G:G) -> 0
A16: Nail Tech Commission (10%) | B16: =SUMIF(Transactions!E:E,"Nail Tech",Transactions!G:G) -> 0
A17: Total Staff Pay (Base + Incentives + Commission) | B17: =B8+B9+B10+B11+B12+B13+B14+B15+B16 -> 0
A18: Total Expenses | B18: =B3+B4+B17 -> 0
A19: Owner Net Income | B19: =B2-B18 -> 0
A21: Staff | B21: Total Sales | C21: Base Salary | D21: Incentive | E21: Commission | F21: Total Pay
A22: Senior Stylist | B22: =B5 -> 0 | C22: =B8 -> 0 | D22: =B11 -> 0 | E22: =B14 -> 0 | F22: =C22+D22+E22 -> 0
A23: Junior Stylist | B23: =B6 -> 0 | C23: =B9 -> 0 | D23: =B12 -> 0 | E23: =B15 -> 0 | F23: =C23+D23+E23 -> 0
A24: Nail Tech | B24: =B7 -> 0 | C24: =B10 -> 0 | D24: =B13 -> 0 | E24: =B16 -> 0 | F24: =C24+D24+E24 -> 0
