Workbook

Sheet PriceList
A1: Category | B1: Service | C1: Price
A2: Hair | B2: Blowdry | C2: 99
A3: Hair | B3: Haircut | C3: 149
A4: Hair | B4: Iron | C4: 199
A5: Hair | B5: Hair Spa | C5: 349
A6: Hair | B6: Hair Botox Treatment | C6: 499
A7: Hair | B7: Keratin Mask | C7: 499
A8: Hair | B8: Color | C8: 699
A9: Hair | B9: Rebond | C9: 1499
A10: Hair | B10: Rebond Hair Botox | C10: 1999
A11: Hair | B11: Rebond / Color | C11: 2199
A12: Hair | B12: Rebond / Color / Brazilian | C12: 3199
A13: Hair | B13: Kerabond | C13: 1999
... A32: Other | B32: Hair & Make up (Wedding/Debut) | C32: 1499

Sheet Settings
A1: Staff Share % | B1: 0.4
A2: Owner Share % | B2: 0.6
A4: Fixed Rent | B4: 15000
A5: Electricity | B5: 5000
A6: Water | B6: 500
A8: Product Cost % of Sales | B8: 0.2
A11: Nail Tech Min Monthly Wage | B11: 7000

Sheet Transactions
A1: Date | B1: Day | C1: Service | D1: Category | E1: Staff | F1: Price | G1: Staff Share (40%) | H1: Owner Share (60%)
A2: 45658 | B2: Wed | C2: Manicure | D2: Nail | E2: Nail Tech | F2: 119 | G2: =IF(E2="Nail Tech",0,F2*Settings!$B$1) -> 0 | H2: =IF(E2="Nail Tech",F2,F2*Settings!$B$2) -> 0
A3: 45658 | B3: Wed | C3: Foot Spa | D3: Nail | E3: Nail Tech | F3: 299 | G3: =IF(E3="Nail Tech",0,F3*Settings!$B$1) -> 0 | H3: =IF(E3="Nail Tech",F3,F3*Settings!$B$2) -> 0
A4: 45658 | B4: Wed | C4: Blowdry | D4: Hair | E4: Senior Stylist | F4: 99 | G4: =IF(E4="Nail Tech",0,F4*Settings!$B$1) -> 0 | H4: =IF(E4="Nail Tech",F4,F4*Settings!$B$2) -> 0
A5: 45658 | B5: Wed | C5: Blowdry | D5: Hair | E5: Junior Stylist | F5: 99 | G5: =IF(E5="Nail Tech",0,F5*Settings!$B$1) -> 0 | H5: =IF(E5="Nail Tech",F5,F5*Settings!$B$2) -> 0
A6: 45658 | B6: Wed | C6: Brazilian | D6: Hair | E6: Junior Stylist | F6: 1499 | G6: =IF(E6="Nail Tech",0,F6*Settings!$B$1) -> 0 | H6: =IF(E6="Nail Tech",F6,F6*Settings!$B$2) -> 0
A7: 45658 | B7: Wed | C7: Balayage / Color | D7: Hair | E7: Junior Stylist | F7: 2499 | G7: =IF(E7="Nail Tech",0,F7*Settings!$B$1) -> 0 | H7: =IF(E7="Nail Tech",F7,F7*Settings!$B$2) -> 0
A8: 45658 | B8: Wed | C8: Blowdry | D8: Hair | E8: Senior Stylist | F8: 99 | G8: =IF(E8="Nail Tech",0,F8*Settings!$B$1) -> 0 | H8: =IF(E8="Nail Tech",F8,F8*Settings!$B$2) -> 0
A9: 45658 | B9: Wed | C9: Iron | D9: Hair | E9: Senior Stylist | F9: 199 | G9: =IF(E9="Nail Tech",0,F9*Settings!$B$1) -> 0 | H9: =IF(E9="Nail Tech",F9,F9*Settings!$B$2) -> 0
A10: 45658 | B10: Wed | C10: Pedicure | D10: Nail | E10: Nail Tech | F10: 149 | G10: =IF(E10="Nail Tech",0,F10*Settings!$B$1) -> 0 | H10: =IF(E10="Nail Tech",F10,F10*Settings!$B$2) -> 0
A11: 45658 | B11: Wed | C11: Keratin Mask | D11: Hair | E11: Senior Stylist | F11: 499 | G11: =IF(E11="Nail Tech",0,F11*Settings!$B$1) -> 0 | H11: =IF(E11="Nail Tech",F11,F11*Settings!$B$2) -> 0
A12: 45658 | B12: Wed | C12: Manicure / Pedicure | D12: Nail | E12: Nail Tech | F12: 269 | G12: =IF(E12="Nail Tech",0,F12*Settings!$B$1) -> 0 | H12: =IF(E12="Nail Tech",F12,F12*Settings!$B$2) -> 0
A13: 45659 | B13: Thu | C13: Nails Extension Ordinary Polish | D13: Nail | E13: Nail Tech | F13: 399 | G13: =IF(E13="Nail Tech",0,F13*Settings!$B$1) -> 0 | H13: =IF(E13="Nail Tech",F13,F13*Settings!$B$2) -> 0
... A281: 45687 | B281: Thu | C281: Nails Extension Gel Polish | D281: Nail | E281: Nail Tech | F281: 599 | G281: =IF(E281="Nail Tech",0,F281*Settings!$B$1) -> 0 | H281: =IF(E281="Nail Tech",F281,F281*Settings!$B$2) -> 0

Sheet Summary
A1: Metric | B1: Amount (PHP)
A2: Total Sales | B2: =SUM(Transactions!F:F) -> 0
A3: Total Staff Salary (Commissions) | B3: =SUM(Transactions!G:G) -> 0
A4: Owner Gross Share | B4: =SUM(Transactions!H:H) -> 0
A5: Product Cost | B5: =B2*Settings!$B$8 -> 0
A6: Fixed Salon Expenses (Rent+Utilities) | B6: =Settings!$B$4+Settings!$B$5+Settings!$B$6 -> 0
A7: Total Expenses | B7: =B14+B5+B6 -> 0
A8: Owner Net Income | B8: =B2-B7 -> 0
A11: Nail Tech Min Monthly Wage (Setting) | B11: =Settings!$B$11 -> 0
A12: Nail Tech Commission (0%) | B12: =0 -> 0
A13: Nail Tech Actual Pay | B13: =MAX(B11,B12) -> 0
A14: Adjusted Total Staff Salary | B14: =B3-B12+B13 -> 0
A17: Staff | B17: Total Sales | C17: Commission (40%)
A18: Senior Stylist | B18: =SUMIF(Transactions!E:E,"Senior Stylist",Transactions!F:F) -> 0 | C18: =B18*Settings!$B$1 -> 0
A19: Junior Stylist | B19: =SUMIF(Transactions!E:E,"Junior Stylist",Transactions!F:F) -> 0 | C19: =B19*Settings!$B$1 -> 0
A20: Nail Tech | B20: =SUMIF(Transactions!E:E,"Nail Tech",Transactions!F:F) -> 0 | C20: =0 -> 0
